mdiskconverter/__init__.py
MdiskConverter-1.8.10.dist-info/LICENSE
MdiskConverter-1.8.10.dist-info/METADATA
MdiskConverter-1.8.10.dist-info/WHEEL
MdiskConverter-1.8.10.dist-info/top_level.txt
MdiskConverter-1.8.10.dist-info/RECORD
