Metadata-Version: 2.1
Name: MdiskConverter
Version: 1.8.10
Summary: Package containing basic functions to build telegram bots.
Home-page: https://github.com
Author: MDISK
License: GNU AFFERO GENERAL PUBLIC LICENSE (v3)
Classifier: Programming Language :: Python :: 3
Classifier: Programming Language :: Python :: 3.6
Classifier: Programming Language :: Python :: 3.7
Classifier: Programming Language :: Python :: 3.8
Classifier: Programming Language :: Python :: 3.9
Classifier: License :: OSI Approved :: GNU General Public License v3 (GPLv3)
Classifier: Operating System :: OS Independent
Requires-Python: >=3.6
License-File: LICENSE
Requires-Dist: pyrogram
Requires-Dist: aiofiles
Requires-Dist: aiohttp
Requires-Dist: requests
